GTkinter/__init__.py
GTkinter/app.py
GTkinter/button.py
GTkinter/enums.py
GTkinter/label.py
GTkinter/layout.py
GTkinter/window.py
gtkinter-0.0.2.dist-info/licenses/LICENSE
gtkinter-0.0.2.dist-info/METADATA
gtkinter-0.0.2.dist-info/WHEEL
gtkinter-0.0.2.dist-info/top_level.txt
gtkinter-0.0.2.dist-info/RECORD
