Metadata-Version: 2.4
Name: GTkinter
Version: 0.0.2
Summary: A very simple and beginner-friendly GTK wrapper
Author-email: Aydin Rahbaran <codewizaard@proton.me>
License:                     GNU GENERAL PUBLIC LICENSE
Project-URL: Homepage, https://github.com/Code-Wizaard/GTkinter
Project-URL: Repository, https://github.com/Code-Wizaard/GTkinter.git
Project-URL: Issues, https://github.com/Code-Wizaard/GTkinter/issues
Keywords: gtk,gui,wrapper,python-gtk,beginner
Classifier: Programming Language :: Python :: 3
Classifier: Operating System :: POSIX :: Linux
Classifier: License :: OSI Approved :: MIT License
Requires-Python: >=3.7
License-File: LICENSE
Requires-Dist: PyGObject
Dynamic: license-file
